flask_zipkin.py
fl_flask_zipkin-0.0.10.dist-info/DESCRIPTION.rst
fl_flask_zipkin-0.0.10.dist-info/METADATA
fl_flask_zipkin-0.0.10.dist-info/RECORD
fl_flask_zipkin-0.0.10.dist-info/WHEEL
fl_flask_zipkin-0.0.10.dist-info/metadata.json
fl_flask_zipkin-0.0.10.dist-info/top_level.txt
