Metadata-Version: 2.0
Name: fl-flask-zipkin
Version: 0.0.10
Summary: An zipkin extension for Flask based on py_zipkin.
Home-page: UNKNOWN
Author: killpanda
Author-email: angus@killpanda.de
License: BSD
Platform: any
Requires-Dist: Flask
Requires-Dist: py-zipkin (>=0.4.0)
Requires-Dist: requests (>=2.11.1)
